count_record_refs.py
CountRecordRefs-0.2.1.dist-info/DESCRIPTION.rst
CountRecordRefs-0.2.1.dist-info/METADATA
CountRecordRefs-0.2.1.dist-info/RECORD
CountRecordRefs-0.2.1.dist-info/WHEEL
CountRecordRefs-0.2.1.dist-info/entry_points.txt
CountRecordRefs-0.2.1.dist-info/metadata.json
CountRecordRefs-0.2.1.dist-info/top_level.txt
