Metadata-Version: 2.0
Name: CountRecordRefs
Version: 0.2.1
Summary: Command-line utility for counting records that refer to a database table in MySQL.
Home-page: https://github.com/jmenglund/CountRecordRefs
Author: Markus Englund
Author-email: jan.markus.englund@gmail.com
License: GPLv3
Keywords: MySQL
Platform: UNKNOWN
Classifier: Development Status :: 5 - Production/Stable
Classifier: Intended Audience :: Developers
Classifier: Intended Audience :: System Administrators
Classifier: Topic :: Database
Classifier: Topic :: Utilities
Classifier: License :: OSI Approved :: GNU General Public License v3 (GPLv3)
Classifier: Operating System :: OS Independent
Classifier: Programming Language :: Python
Classifier: Programming Language :: Python :: 2
Classifier: Programming Language :: Python :: 2.7
Classifier: Programming Language :: Python :: 3
Classifier: Programming Language :: Python :: 3.3
Classifier: Programming Language :: Python :: 3.4
Classifier: Programming Language :: Python :: 3.5
Requires-Dist: pymysql
